kpt/__init__.py
kpt/model/__init__.py
kpt/model/skeleton.py
kpt-0.0.7.dist-info/METADATA
kpt-0.0.7.dist-info/WHEEL
kpt-0.0.7.dist-info/top_level.txt
kpt-0.0.7.dist-info/RECORD
