Metadata-Version: 2.1
Name: kpt
Version: 0.0.7
Summary: Kinematics with PyTorch
Home-page: https://github.com/jihoonerd/Kinematics-PyTorch
Author: Jihoon Kim
Author-email: jihoon_kim@outlook.com
License: UNKNOWN
Platform: UNKNOWN
Requires-Dist: numpy
Requires-Dist: torch
Requires-Dist: pytorch3d
